UzLemmatizer/UzLemmatizer.py
UzLemmatizer/__init__.py
UzLemmatizer/affixes.csv
UzLemmatizer/exception_stems.csv
UzLemmatizer/lemma_map.csv
UzLemmatizer/non_affixed_stems.csv
UzLemmatizer/number_stems.csv
UzLemmatizer/small_stems.csv
UzLemmatizer-0.0.1.dist-info/LICENSE
UzLemmatizer-0.0.1.dist-info/METADATA
UzLemmatizer-0.0.1.dist-info/WHEEL
UzLemmatizer-0.0.1.dist-info/top_level.txt
UzLemmatizer-0.0.1.dist-info/RECORD
