Metadata-Version: 2.1
Name: UzLemmatizer
Version: 0.0.1
Summary: UzLemmatizer: A Stemmer and Lemmatizer Tool for Uzbek Language
Home-page: https://github.com/UlugbekSalaev/UzLemmatizer
Author: Ulugbek Salaev
Author-email: ulugbek0302@gmail.com
License: UNKNOWN
Project-URL: Bug Tracker, https://github.com/UlugbekSalaev/UzLemmatizer/issues
Keywords: mophology,uzbek-language,stemmer,lemmatize,part-of-speech-tag
Platform: UNKNOWN
Classifier: Programming Language :: Python :: 3
Classifier: License :: OSI Approved :: MIT License
Classifier: Operating System :: OS Independent
Requires-Python: >=3.6
License-File: LICENSE
